dj_secret_settings/__init__.py
dj_secret_settings/fetchers/__init__.py
dj_secret_settings/fetchers/from_gsm.py
dj_secret_settings/settings_store.py
dj_secret_settings/stores/__init__.py
dj_secret_settings/stores/from_environment.py
dj_secret_settings/stores/from_json.py
dj_secret_settings-0.1.1.dist-info/LICENSE
dj_secret_settings-0.1.1.dist-info/WHEEL
dj_secret_settings-0.1.1.dist-info/METADATA
dj_secret_settings-0.1.1.dist-info/RECORD
