Metadata-Version: 2.1
Name: dj-secret-settings
Version: 0.1.1
Summary: Provide settings to Django from a secret store such as Google Cloud Secrets
Home-page: https://github.com/damycra/dj_secret_settings
License: MIT
Keywords: django,settings,cloud,secrets
Author: Steven Davidson
Author-email: github@damycra.com
Requires-Python: >=3.7,<4.0
Classifier: Development Status :: 4 - Beta
Classifier: Framework :: Django
Classifier: Intended Audience :: Developers
Classifier: License :: OSI Approved :: MIT License
Classifier: Programming Language :: Python :: 3
Classifier: Programming Language :: Python :: 3.10
Classifier: Programming Language :: Python :: 3.7
Classifier: Programming Language :: Python :: 3.8
Classifier: Programming Language :: Python :: 3.9
Classifier: Topic :: Software Development :: Libraries :: Python Modules
Provides-Extra: google_secret_manager
Requires-Dist: google-cloud-secret-manager (>=2.7.0,<3.0.0); extra == "google_secret_manager"
Project-URL: Repository, https://github.com/damycra/dj_secret_settings
